LICENSE
README.rst
setup.py
opencv_wrap/__init__.py
opencv_wrap/cv2Decorator.py
opencv_wrap.egg-info/PKG-INFO
opencv_wrap.egg-info/SOURCES.txt
opencv_wrap.egg-info/dependency_links.txt
opencv_wrap.egg-info/not-zip-safe
opencv_wrap.egg-info/requires.txt
opencv_wrap.egg-info/top_level.txt
opencv_wrap/detectors/Face.py
opencv_wrap/detectors/Hand.py
opencv_wrap/detectors/Pose.py
opencv_wrap/detectors/__init__.py
opencv_wrap/utils/__init__.py
opencv_wrap/utils/base.py
opencv_wrap/utils/helper.py