Metadata-Version: 2.1
Name: opencv-wrap
Version: 0.1.2
Summary: Working with opencv can be quite a hussel, a lot of boiler code, nested functions for specific use cases, this package is designed to make it easier to work with opencv, while focusing on the main task in hand. best for prototyping and quick testing. second part is speed and performance, this package is designed to be fast and efficient.
Home-page: https://github.com/rishi23root/opencv_wrap
Author: rishi23root
Author-email: rishi23root@gmail.com
License: MIT
Platform: UNKNOWN
Classifier: Intended Audience :: Developers
Classifier: License :: OSI Approved :: MIT License
Classifier: Operating System :: OS Independent
Classifier: Programming Language :: Python :: 3.7
Classifier: Programming Language :: Python :: 3.8
Classifier: Programming Language :: Python :: 3.9
Classifier: Programming Language :: Python :: 3.10
License-File: LICENSE
